{
  "code": 0,
  "msg": "suc",
  "tips": null,
  "data": {
    "type": "category",
    "id": "1609",
    "name": "大地测量技术其他学科",
    "lemmaId": "39886081931374088",
    "edited": false,
    "partnerNum": 0,
    "editedLemmaNum": 0,
    "lemmaNum": 1,
    "allCategoryLemmaNum": 0,
    "parentId": "1605",
    "spread": false,
    "children": [
      {
        "type": "lemma",
        "id": "39886081931374088",
        "name": "大地测量技术其他学科",
        "lemmaId": "0",
        "edited": false,
        "partnerNum": 0,
        "editedLemmaNum": 0,
        "lemmaNum": 0,
        "allCategoryLemmaNum": 0,
        "parentId": "1609",
        "spread": false,
        "children": null
      }
    ]
  },
  "success": true
}