{
  "code": 0,
  "msg": "suc",
  "tips": null,
  "data": {
    "type": "category",
    "id": "759",
    "name": "城市地质学",
    "lemmaId": "34555506450256132",
    "edited": false,
    "partnerNum": 0,
    "editedLemmaNum": 0,
    "lemmaNum": 1,
    "allCategoryLemmaNum": 0,
    "parentId": "585",
    "spread": false,
    "children": [
      {
        "type": "lemma",
        "id": "34555506450256132",
        "name": "城市地质学",
        "lemmaId": "0",
        "edited": false,
        "partnerNum": 0,
        "editedLemmaNum": 0,
        "lemmaNum": 0,
        "allCategoryLemmaNum": 0,
        "parentId": "759",
        "spread": false,
        "children": null
      }
    ]
  },
  "success": true
}