{
  "code": 0,
  "msg": "suc",
  "tips": null,
  "data": {
    "type": "category",
    "id": "969",
    "name": "希尔伯特空间",
    "lemmaId": "39886064097193478",
    "edited": false,
    "partnerNum": 0,
    "editedLemmaNum": 0,
    "lemmaNum": 1,
    "allCategoryLemmaNum": 0,
    "parentId": "965",
    "spread": false,
    "children": [
      {
        "type": "lemma",
        "id": "39886064097193478",
        "name": "希尔伯特空间",
        "lemmaId": "0",
        "edited": false,
        "partnerNum": 0,
        "editedLemmaNum": 0,
        "lemmaNum": 0,
        "allCategoryLemmaNum": 0,
        "parentId": "969",
        "spread": false,
        "children": null
      }
    ]
  },
  "success": true
}